vllm_semantic_router_bench/__init__.py
vllm_semantic_router_bench/bench_plot.py
vllm_semantic_router_bench/cli.py
vllm_semantic_router_bench/dataset_factory.py
vllm_semantic_router_bench/dataset_interface.py
vllm_semantic_router_bench/router_reason_bench_multi_dataset.py
vllm_semantic_router_bench/test_package.py
vllm_semantic_router_bench/dataset_implementations/__init__.py
vllm_semantic_router_bench/dataset_implementations/arc_dataset.py
vllm_semantic_router_bench/dataset_implementations/commonsenseqa_dataset.py
vllm_semantic_router_bench/dataset_implementations/gpqa_dataset.py
vllm_semantic_router_bench/dataset_implementations/hellaswag_dataset.py
vllm_semantic_router_bench/dataset_implementations/mmlu_dataset.py
vllm_semantic_router_bench/dataset_implementations/truthfulqa_dataset.py
vllm_semantic_router_bench-1.0.0.dist-info/licenses/LICENSE
vllm_semantic_router_bench-1.0.0.dist-info/METADATA
vllm_semantic_router_bench-1.0.0.dist-info/WHEEL
vllm_semantic_router_bench-1.0.0.dist-info/entry_points.txt
vllm_semantic_router_bench-1.0.0.dist-info/top_level.txt
vllm_semantic_router_bench-1.0.0.dist-info/RECORD
