Metadata-Version: 2.4
Name: vllm-semantic-router-bench
Version: 1.0.0
Summary: Comprehensive benchmark suite for semantic router vs direct vLLM evaluation across multiple reasoning datasets
Home-page: https://github.com/vllm-project/semantic-router
Author: vLLM Semantic Router Team
License: Apache-2.0
Project-URL: Homepage, https://github.com/vllm-project/semantic-router
Project-URL: Documentation, https://vllm-semantic-router.com
Project-URL: Repository, https://github.com/vllm-project/semantic-router
Project-URL: Bug Tracker, https://github.com/vllm-project/semantic-router/issues
Keywords: vllm-semantic-router,benchmark,vllm,llm,evaluation,reasoning,multiple-choice,mmlu,arc,gpqa,commonsense,hellaswag,truthfulqa
Classifier: Development Status :: 4 - Beta
Classifier: Intended Audience :: Developers
Classifier: Intended Audience :: Science/Research
Classifier: License :: OSI Approved :: Apache Software License
Classifier: Operating System :: OS Independent
Classifier: Programming Language :: Python :: 3
Classifier: Programming Language :: Python :: 3.8
Classifier: Programming Language :: Python :: 3.9
Classifier: Programming Language :: Python :: 3.10
Classifier: Programming Language :: Python :: 3.11
Classifier: Programming Language :: Python :: 3.12
Classifier: Topic :: Scientific/Engineering :: Artificial Intelligence
Classifier: Topic :: Software Development :: Testing
Classifier: Topic :: System :: Benchmark
Requires-Python: >=3.8
License-File: LICENSE
Requires-Dist: openai>=1.0.0
Requires-Dist: datasets>=2.14.0
Requires-Dist: pandas>=1.5.0
Requires-Dist: numpy>=1.21.0
Requires-Dist: tqdm>=4.64.0
Requires-Dist: requests>=2.28.0
Requires-Dist: matplotlib>=3.5.0
Requires-Dist: seaborn>=0.11.0
Provides-Extra: dev
Requires-Dist: pytest>=6.0; extra == "dev"
Requires-Dist: black>=22.0; extra == "dev"
Requires-Dist: flake8>=4.0; extra == "dev"
Requires-Dist: mypy>=0.950; extra == "dev"
Requires-Dist: pre-commit>=2.15.0; extra == "dev"
Provides-Extra: plotting
Requires-Dist: matplotlib>=3.5.0; extra == "plotting"
Requires-Dist: seaborn>=0.11.0; extra == "plotting"
Dynamic: home-page
Dynamic: license-file
Dynamic: requires-python
